yaml_modify/__init__.py
yaml_modify/backup_manager.py
yaml_modify/main.py
yaml_modify/orchestrator.py
yaml_modify/test_orchestrator.py
yaml_modify/yaml_handler.py
yaml_modify-0.2.7.dist-info/LICENSE
yaml_modify-0.2.7.dist-info/METADATA
yaml_modify-0.2.7.dist-info/WHEEL
yaml_modify-0.2.7.dist-info/entry_points.txt
yaml_modify-0.2.7.dist-info/top_level.txt
yaml_modify-0.2.7.dist-info/RECORD
