Metadata-Version: 2.1
Name: yaml-modify
Version: 0.2.7
Summary: A CLI tool for modifying YAML files, managing backups, and orchestrating test sequences.
Home-page: https://github.com/geonsonatt/yaml_modify
Author: Dad Macintosh
Author-email: gerano.03@mail.ru
License: UNKNOWN
Platform: UNKNOWN
Classifier: Programming Language :: Python :: 3
Classifier: License :: OSI Approved :: MIT License
Classifier: Operating System :: OS Independent
Requires-Python: >=3.6
License-File: LICENSE
Requires-Dist: argparse
Requires-Dist: pyyaml
